{"Added":[],"Modified":[{"Id":50092,"Kind":12,"Name":"Post. Sales Invoice Lines","PackagePath":"/src/src/page/Pag50092.PostSalesInvoiceLines.al"},{"Id":50055,"Kind":12,"Name":"Location Service","PackagePath":"/src/src/page/Pag50055.LocationService.al"},{"Id":50000,"Kind":12,"Name":"Hanning Setup","PackagePath":"/src/src/page/Pag50000.HanningSetup.al"},{"Id":50078,"Kind":12,"Name":"Internal Job Item Category","PackagePath":"/src/src/page/Pag50078.InternalJobItemCategory.al"},{"Id":50090,"Kind":12,"Name":"Mapping Sach Deb Kred","PackagePath":"/src/src/page/Pag50090.MappingSachDebKred.al"},{"Id":50088,"Kind":12,"Name":"Cerificate Subpage","PackagePath":"/src/src/page/Pag50088.CerificateSubpage.al"},{"Id":50086,"Kind":12,"Name":"GIMCertificate List","PackagePath":"/src/src/page/Pag50086.CertificateList.al"},{"Id":50096,"Kind":12,"Name":"Arch. Sales Lines 2","PackagePath":"/src/src/page/Pag50096.ArchSalesLines2.al"},{"Id":50058,"Kind":12,"Name":"Post. Service Cr. Memo  Lines","PackagePath":"/src/src/page/Pag50058.PostServiceCrMemoLines.al"},{"Id":50056,"Kind":12,"Name":"Service Lines 2","PackagePath":"/src/src/page/Pag50056.ServiceLines2.al"},{"Id":50095,"Kind":12,"Name":"Mahnungsvorschlagsübersicht","PackagePath":"/src/src/page/Pag50095.Mahnungsvorschlagsbersicht.al"},{"Id":50093,"Kind":12,"Name":"Post. Sales Credit Memo Lines","PackagePath":"/src/src/page/Pag50093.PostSalesCreditMemoLines.al"},{"Id":50054,"Kind":12,"Name":"Production Groups","PackagePath":"/src/src/page/Pag50054.ProductionGroups.al"},{"Id":50091,"Kind":12,"Name":"Sales Lines 2","PackagePath":"/src/src/page/Pag50091.SalesLines2.al"},{"Id":50087,"Kind":12,"Name":"GIMCertificate","PackagePath":"/src/src/page/Pag50087.Certificate.al"},{"Id":50099,"Kind":12,"Name":"FieldsTable","PackagePath":"/src/src/page/Pag50099.FieldsTable.al"},{"Id":50045,"Kind":12,"Name":"RMD Einrichtung","PackagePath":"/src/src/page/Pag50045.RMDEinrichtung.al"},{"Id":50059,"Kind":12,"Name":"GIMPrüfzertifikatszeilen","PackagePath":"/src/src/page/Pag50059.GIMPrfzertifikatszeilen.al"},{"Id":50057,"Kind":12,"Name":"Post. Service Invoice Lines","PackagePath":"/src/src/page/Pag50057.PostServiceInvoiceLines.al"},{"Id":50018,"Kind":12,"Name":"Kategorie","PackagePath":"/src/src/page/Pag50018.Kategorie.al"},{"Id":50094,"Kind":12,"Name":"Auftrag-FA","PackagePath":"/src/src/page/Pag50094.AuftragFA.al"}],"Removed":[]}